testpypipekuk/__init__.py
testpypipekuk/m_mod_ek.py
testpypipekuk-0.0.1.dist-info/License.txt.py
testpypipekuk-0.0.1.dist-info/METADATA
testpypipekuk-0.0.1.dist-info/WHEEL
testpypipekuk-0.0.1.dist-info/top_level.txt
testpypipekuk-0.0.1.dist-info/RECORD
