Metadata-Version: 2.1
Name: testpypipekuk
Version: 0.0.1
Summary: My test package
Author-email: EK <ewelina1018@gmail.com>
Keywords: testpypipekuk,name
Classifier: Framework :: Pytest
Classifier: Framework :: Trac
Requires-Python: >=3.0
License-File: License.txt.py
Requires-Dist: numpy
